idefixx/__init__.py
idefixx/idefixx.py
idefixx-0.15.dist-info/LICENSE.txt
idefixx-0.15.dist-info/METADATA
idefixx-0.15.dist-info/WHEEL
idefixx-0.15.dist-info/top_level.txt
idefixx-0.15.dist-info/RECORD
